LICENSE
server.js
setup.py
chrome-extension/128.png
chrome-extension/64.png
chrome-extension/background.html
chrome-extension/bug-icon.png
chrome-extension/client.js
chrome-extension/manifest.json
chrome-extension/options.html
chrome-extension/options.js
chrome-extension/popup.html
chrome-extension/socket.io.js
chrome-extension/socket.io.min.js
demo/__init__.py
demo/manage.py
demo/server-ws.js
demo/settings.py
demo/urls.py
demo/media/socket.io.min.js
demo/templates/index.html
demo/templates/login_notification.html
desktopnotifications/__init__.py
desktopnotifications/admin.py
desktopnotifications/forms.py
desktopnotifications/models.py
desktopnotifications/notification.py
desktopnotifications/tests.py
desktopnotifications/urls.py
desktopnotifications/views.py
django_desktop_notifications.egg-info/PKG-INFO
django_desktop_notifications.egg-info/SOURCES.txt
django_desktop_notifications.egg-info/dependency_links.txt
django_desktop_notifications.egg-info/not-zip-safe
django_desktop_notifications.egg-info/requires.txt
django_desktop_notifications.egg-info/top_level.txt