Metadata-Version: 1.0
Name: django-desktop-notifications
Version: 0.3
Summary: Django / NodeJS / Chrome / websocket ultra fast desktop notifications
Home-page: http://code.google.com/p/django-desktop-notifications/
Author: Laurent Coustet
Author-email: ed@zehome.com
License: UNKNOWN
Platform: UNKNOWN
Classifier: Framework :: Django
Classifier: Intended Audience :: Developers
Classifier: Intended Audience :: System Administrators
Classifier: Intended Audience :: Information Technology
Classifier: Operating System :: OS Independent
Classifier: Topic :: Software Development
